Metadata-Version: 2.4
Name: llama-index-vector-stores-tencentvectordb
Version: 0.4.2
Summary: llama-index vector_stores tencentvectordb integration
Author-email: Your Name <you@example.com>
License-Expression: MIT
License-File: LICENSE
Requires-Python: <4.0,>=3.9
Requires-Dist: llama-index-core<0.15,>=0.13.0
Requires-Dist: tcvectordb<2,>=1.3.13
